{"cameraMode":{"drawMode":0,"name":"Shaded","section":"Shading Mode"},"sceneLighting":true,"audioPlay":false,"sceneViewState":{"showFog":true,"showMaterialUpdate":false,"showSkybox":true,"showFlares":true,"showImageEffects":true,"showParticleSystems":true},"in2DMode":false,"pivot":{"x":3.981874704360962,"y":1.1975011825561524,"z":-2.339998722076416},"rotation":{"x":-0.3967186212539673,"y":0.07779400050640106,"z":-0.03376521170139313,"w":-0.9140191674232483},"size":38.91346740722656,"orthographic":false}